{"productAttr":null,"productCommentSummary":{"goodRateShow":97,"poorRateShow":2,"poorCountStr":"800+","averageScore":5,"generalCountStr":"700+","showCount":8700,"showCountStr":"8700+","goodCount":50000,"generalRate":0.014,"generalCount":700,"skuId":3133817,"goodCountStr":"5万+","poorRate":0.017,"afterCount":50,"goodRateStyle":145,"poorCount":800,"skuIds":null,"poorRateStyle":3,"generalRateStyle":2,"commentCountStr":"5.1万+","commentCount":51000,"productId":3133817,"afterCountStr":"50+","goodRate":0.969,"generalRateShow":1},"hotCommentTagStatistics":[{"id":1356036,"name":"系统流畅","status":0,"rid":15226,"productId":3133817,"count":870,"created":"2016-09-16 16:29:27","modified":"2017-03-02 23:00:02","type":0},{"id":1357450,"name":"外观漂亮","status":0,"rid":15225,"productId":3133817,"count":775,"created":"2016-09-18 09:29:54","modified":"2017-03-02 10:19:11","type":0},{"id":1357482,"name":"反应快","status":0,"rid":15224,"productId":3133817,"count":733,"created":"2016-09-18 09:54:40","modified":"2017-03-02 15:19:29","type":0},{"id":1357480,"name":"功能齐全","status":0,"rid":15231,"productId":3133817,"count":632,"created":"2016-09-18 09:54:40","modified":"2017-03-02 17:36:00","type":0},{"id":1356171,"name":"指纹识别","status":0,"rid":31384,"productId":3133817,"count":542,"created":"2016-09-16 19:33:13","modified":"2017-03-02 22:57:21","type":0},{"id":1356035,"name":"照相不错","status":0,"rid":15223,"productId":3133817,"count":531,"created":"2016-09-16 16:29:27","modified":"2017-03-01 15:38:57","type":0},{"id":1357481,"name":"分辨率高","status":0,"rid":15232,"productId":3133817,"count":453,"created":"2016-09-18 09:54:40","modified":"2017-03-02 10:59:53","type":0},{"id":1358321,"name":"音质好","status":0,"rid":15234,"productId":3133817,"count":442,"created":"2016-09-18 22:56:02","modified":"2017-03-01 15:38:57","type":0},{"id":1365225,"name":"通话质量好","status":0,"rid":15235,"productId":3133817,"count":424,"created":"2016-09-26 09:56:15","modified":"2017-03-02 22:43:18","type":0},{"id":1357451,"name":"信号稳定","status":0,"rid":15236,"productId":3133817,"count":415,"created":"2016-09-18 09:29:54","modified":"2017-03-02 10:59:53","type":0}],"jwotestProduct":"99","maxPage":5198,"score":0,"soType":5,"imageListCount":500,"vTagStatistics":[],"comments":[{"id":1942819289,"guid":"21b076eb-7774-4c1a-9dd4-3e3f76120a9a","content":"容易刮伤，差评！","creationTime":"2016-10-25 09:25:42","isTop":false,"referenceId":"3133817","referenceImage":"jfs/t3298/58/1622979569/120892/64989235/57d0d400Nfd249af4.jpg","referenceName":"Apple iPhone 7 (A1660) 32G 黑色 移动联通电信4G手机","referenceTime":"2016-10-17 22:24:30","referenceType":"Product","referenceTypeId":0,"firstCategory":9987,"secondCategory":653,"thirdCategory":655,"replyCount":0,"score":2,"status":1,"title":"","usefulVoteCount":0,"uselessVoteCount":0,"userImage":"storage.360buyimg.com/i.imageUpload/6a645f3737633337663832363736323031343838313134323338373732_sma.jpg","userImageUrl":"storage.360buyimg.com/i.imageUpload/6a645f3737633337663832363736323031343838313134323338373732_sma.jpg","userLevelId":"62","userProvince":"","viewCount":0,"orderId":0,"isReplyGrade":false,"nickname":"凸***二","userClient":22,"productColor":"黑色","productSize":"iPhone 7","integral":0,"userImgFlag":1,"anonymousFlag":1,"userLevelName":"金牌会员","plusAvailable":103,"productSales":[],"recommend":false,"userLevelColor":"#666666","userClientShow":"来自手机QQ购物","isMobile":false,"days":8,"afterDays":0},{"id":1942792439,"guid":"ca16a42e-fae0-4d6a-bcd3-5e4b23934204","content":"很满意","creationTime":"2016-10-25 09:17:12","isTop":false,"referenceId":"3133817","referenceImage":"jfs/t3298/58/1622979569/120892/64989235/57d0d400Nfd249af4.jpg","referenceName":"Apple iPhone 7 (A1660) 32G 黑色 移动联通电信4G手机","referenceTime":"2016-10-23 15:30:20","referenceType":"Product","referenceTypeId":0,"firstCategory":9987,"secondCategory":653,"thirdCategory":655,"replyCount":0,"score":5,"status":1,"title":"","usefulVoteCount":0,"uselessVoteCount":0,"userImage":"misc.360buyimg.com/lib/img/u/b61.gif","userImageUrl":"misc.360buyimg.com/lib/img/u/b61.gif","userLevelId":"61","userProvince":"","viewCount":0,"orderId":0,"isReplyGrade":false,"nickname":"j***1","userClient":2,"productColor":"黑色","productSize":"iPhone 7","integral":0,"userImgFlag":0,"anonymousFlag":1,"userLevelName":"银牌会员","plusAvailable":0,"productSales":[],"recommend":false,"userLevelColor":"#666666","userClientShow":"来自京东iPhone客户端","isMobile":true,"days":2,"afterDays":0},{"id":1942782876,"guid":"6d7df1e2-f876-47d3-b3f0-d9351f44e42c","content":"京东自营，值得信赖，速度够快，有保障！不是托?","creationTime":"2016-10-25 09:14:06","isTop":false,"referenceId":"3133817","referenceImage":"jfs/t3298/58/1622979569/120892/64989235/57d0d400Nfd249af4.jpg","referenceName":"Apple iPhone 7 (A1660) 32G 黑色 移动联通电信4G手机","referenceTime":"2016-10-18 14:55:38","referenceType":"Product","referenceTypeId":0,"firstCategory":9987,"secondCategory":653,"thirdCategory":655,"replyCount":0,"score":5,"status":1,"title":"","usefulVoteCount":0,"uselessVoteCount":0,"userImage":"storage.360buyimg.com/i.imageUpload/6a645f3433646464656262333961386231343736393335323831323333_sma.jpg","userImageUrl":"storage.360buyimg.com/i.imageUpload/6a645f3433646464656262333961386231343736393335323831323333_sma.jpg","userLevelId":"62","userProvince":"","viewCount":0,"orderId":0,"isReplyGrade":false,"nickname":"jd_180022gkc","userClient":2,"productColor":"黑色","productSize":"iPhone 7","integral":-20,"userImgFlag":1,"anonymousFlag":0,"userLevelName":"PLUS会员","plusAvailable":201,"productSales":[],"recommend":false,"userLevelColor":"#e1a10a","userClientShow":"来自京东iPhone客户端","isMobile":true,"days":7,"afterDays":0},{"id":1942780865,"guid":"c8544f04-f2e8-4ef2-8d69-962ca64c1334","content":"物流超给力，手机也没有黄频噪音问题，很满意此次购物","creationTime":"2016-10-25 09:13:23","isTop":false,"referenceId":"3133817","referenceImage":"jfs/t3298/58/1622979569/120892/64989235/57d0d400Nfd249af4.jpg","referenceName":"Apple iPhone 7 (A1660) 32G 黑色 移动联通电信4G手机","referenceTime":"2016-10-16 20:40:43","referenceType":"Product","referenceTypeId":0,"firstCategory":9987,"secondCategory":653,"thirdCategory":655,"replyCount":0,"score":5,"status":1,"title":"","usefulVoteCount":0,"uselessVoteCount":0,"userImage":"storage.360buyimg.com/i.imageUpload/77647a4c6a75645758596c6d706d31343535323435353036373732_sma.jpg","userImageUrl":"storage.360buyimg.com/i.imageUpload/77647a4c6a75645758596c6d706d31343535323435353036373732_sma.jpg","userLevelId":"62","userProvince":"","viewCount":0,"orderId":0,"isReplyGrade":false,"nickname":"放***吗","userClient":2,"productColor":"黑色","productSize":"iPhone 7","integral":-20,"userImgFlag":1,"anonymousFlag":1,"userLevelName":"金牌会员","plusAvailable":103,"productSales":[],"recommend":false,"userLevelColor":"#666666","userClientShow":"来自京东iPhone客户端","isMobile":true,"days":9,"afterDays":0},{"id":1942769775,"guid":"7534ad9f-6b01-4211-aa6c-af6b96ac20a5","content":"挺满意的，买来没出现网上看到的那些问题！","creationTime":"2016-10-25 09:09:25","isTop":false,"referenceId":"3133817","referenceImage":"jfs/t3298/58/1622979569/120892/64989235/57d0d400Nfd249af4.jpg","referenceName":"Apple iPhone 7 (A1660) 32G 黑色 移动联通电信4G手机","referenceTime":"2016-10-19 19:23:02","referenceType":"Product","referenceTypeId":0,"firstCategory":9987,"secondCategory":653,"thirdCategory":655,"replyCount":0,"score":5,"status":1,"title":"","usefulVoteCount":0,"uselessVoteCount":0,"userImage":"misc.360buyimg.com/lib/img/u/b62.gif","userImageUrl":"misc.360buyimg.com/lib/img/u/b62.gif","userLevelId":"62","userProvince":"广东","viewCount":0,"orderId":0,"isReplyGrade":false,"nickname":"j***s","userClient":2,"productColor":"黑色","productSize":"iPhone 7","integral":-20,"userImgFlag":0,"anonymousFlag":1,"userLevelName":"金牌会员","plusAvailable":0,"productSales":[],"recommend":false,"userLevelColor":"#666666","userClientShow":"来自京东iPhone客户端","isMobile":true,"days":6,"afterDays":0},{"id":1942762053,"guid":"f0adec1c-db68-40f7-bd14-760a038f5ebd","content":"服务一流，送老婆的，不错的选择&hellip;&hellip;&hellip;&hellip;","creationTime":"2016-10-25 09:06:48","isTop":false,"referenceId":"3133817","referenceImage":"jfs/t3298/58/1622979569/120892/64989235/57d0d400Nfd249af4.jpg","referenceName":"Apple iPhone 7 (A1660) 32G 黑色 移动联通电信4G手机","referenceTime":"2016-10-21 23:48:37","referenceType":"Product","referenceTypeId":0,"firstCategory":9987,"secondCategory":653,"thirdCategory":655,"replyCount":0,"score":5,"status":1,"title":"","usefulVoteCount":0,"uselessVoteCount":0,"userImage":"storage.360buyimg.com/i.imageUpload/755f3732373932653230626663313031343734383937343031363238_sma.jpg","userImageUrl":"storage.360buyimg.com/i.imageUpload/755f3732373932653230626663313031343734383937343031363238_sma.jpg","userLevelId":"105","userProvince":"","viewCount":0,"orderId":0,"isReplyGrade":false,"nickname":"j***5","userClient":2,"productColor":"黑色","productSize":"iPhone 7","integral":-20,"userImgFlag":1,"anonymousFlag":1,"userLevelName":"钻石会员","plusAvailable":103,"productSales":[],"recommend":false,"userLevelColor":"#666666","userClientShow":"来自京东iPhone客户端","isMobile":true,"days":4,"afterDays":0},{"id":1942719990,"guid":"068377c7-737b-45d7-8e78-28a98db09b16","content":"目前不错","creationTime":"2016-10-25 08:49:11","isTop":false,"referenceId":"3133817","referenceImage":"jfs/t3298/58/1622979569/120892/64989235/57d0d400Nfd249af4.jpg","referenceName":"Apple iPhone 7 (A1660) 32G 黑色 移动联通电信4G手机","referenceTime":"2016-10-23 22:34:21","referenceType":"Product","referenceTypeId":0,"firstCategory":9987,"secondCategory":653,"thirdCategory":655,"replyCount":0,"score":5,"status":1,"title":"","usefulVoteCount":0,"uselessVoteCount":0,"userImage":"misc.360buyimg.com/lib/img/u/b62.gif","userImageUrl":"misc.360buyimg.com/lib/img/u/b62.gif","userLevelId":"62","userProvince":"","viewCount":0,"orderId":0,"isReplyGrade":false,"nickname":"菲***1","userClient":2,"images":[{"id":218027524,"associateId":136017733,"productId":0,"imgUrl":"//img30.360buyimg.com/n0/s128x96_jfs/t3358/293/477575993/87135/bb2fdac/580eac22Na6994b71.jpg","available":1,"pin":"","dealt":0,"imgTitle":"","isMain":0}],"showOrderComment":{"id":136017733,"guid":"0e499715-0b0e-4914-903f-650279e55171","content":"目前不错<div class='uploadimgdiv'><img class='uploadimg' border='0'  src='http://img30.360buyimg.com/shaidan/jfs/t3358/293/477575993/87135/bb2fdac/580eac22Na6994b71.jpg' /></div>","creationTime":"2016-10-25 08:49:38","isTop":false,"referenceId":"3133817","referenceType":"Order","referenceTypeId":0,"firstCategory":0,"secondCategory":0,"thirdCategory":0,"replyCount":0,"score":0,"status":1,"title":"目前不错","usefulVoteCount":0,"uselessVoteCount":0,"userProvince":"","viewCount":0,"orderId":0,"isReplyGrade":false,"userClient":2,"isDeal":1,"integral":-20,"userImgFlag":0,"anonymousFlag":1,"recommend":false,"userLevelColor":"#666666","userClientShow":"来自京东iPhone客户端","isMobile":true},"mergeOrderStatus":2,"discussionId":136017733,"productColor":"黑色","productSize":"iPhone 7","imageCount":1,"integral":0,"userImgFlag":0,"anonymousFlag":1,"userLevelName":"金牌会员","plusAvailable":0,"productSales":[],"recommend":false,"userLevelColor":"#666666","userClientShow":"来自京东iPhone客户端","isMobile":true,"days":2,"afterDays":0},{"id":1942712386,"guid":"65d9b572-6245-496f-9de7-e482ed0a3056","content":"速度很快，刚收到未使用。","creationTime":"2016-10-25 08:45:31","isTop":false,"referenceId":"3133817","referenceImage":"jfs/t3298/58/1622979569/120892/64989235/57d0d400Nfd249af4.jpg","referenceName":"Apple iPhone 7 (A1660) 32G 黑色 移动联通电信4G手机","referenceTime":"2016-10-24 17:38:21","referenceType":"Product","referenceTypeId":0,"firstCategory":9987,"secondCategory":653,"thirdCategory":655,"replyCount":0,"score":5,"status":1,"title":"","usefulVoteCount":0,"uselessVoteCount":0,"userImage":"storage.360buyimg.com/i.imageUpload/3532323234313236315f6d31343631383932343637303032_sma.jpg","userImageUrl":"storage.360buyimg.com/i.imageUpload/3532323234313236315f6d31343631383932343637303032_sma.jpg","userLevelId":"62","userProvince":"广东","viewCount":0,"orderId":0,"isReplyGrade":false,"nickname":"W***u","userClient":4,"productColor":"黑色","productSize":"iPhone 7","integral":-20,"userImgFlag":1,"anonymousFlag":1,"userLevelName":"金牌会员","plusAvailable":0,"productSales":[],"recommend":false,"userLevelColor":"#666666","userClientShow":"来自京东Android客户端","isMobile":true,"days":1,"afterDays":0},{"id":1942710582,"guid":"a1bacca2-8319-4000-bf02-cec9cca5954f","content":"挺好的，及时收到货，使用一段时间了，很棒??????????！","creationTime":"2016-10-25 08:44:32","isTop":false,"referenceId":"3133817","referenceImage":"jfs/t3298/58/1622979569/120892/64989235/57d0d400Nfd249af4.jpg","referenceName":"Apple iPhone 7 (A1660) 32G 黑色 移动联通电信4G手机","referenceTime":"2016-10-11 11:42:38","referenceType":"Product","referenceTypeId":0,"firstCategory":9987,"secondCategory":653,"thirdCategory":655,"replyCount":0,"score":5,"status":1,"title":"","usefulVoteCount":0,"uselessVoteCount":0,"userImage":"storage.360buyimg.com/i.imageUpload/36323335393839362d36343631373331343737323339373239353637_sma.jpg","userImageUrl":"storage.360buyimg.com/i.imageUpload/36323335393839362d36343631373331343737323339373239353637_sma.jpg","userLevelId":"62","userProvince":"","viewCount":0,"orderId":0,"isReplyGrade":false,"nickname":"p***0","userClient":2,"productColor":"黑色","productSize":"iPhone 7","integral":-20,"userImgFlag":1,"anonymousFlag":1,"userLevelName":"金牌会员","plusAvailable":0,"productSales":[],"recommend":false,"userLevelColor":"#666666","userClientShow":"来自京东iPhone客户端","isMobile":true,"days":14,"afterDays":0},{"id":1942626903,"guid":"927c26d2-8eab-4785-a3a3-08697658df1b","content":"感觉上还可以毕竟京东自己的货 支持京东。用了一下午没有发现什么特别的问题","creationTime":"2016-10-25 07:51:46","isTop":false,"referenceId":"3133817","referenceImage":"jfs/t3298/58/1622979569/120892/64989235/57d0d400Nfd249af4.jpg","referenceName":"Apple iPhone 7 (A1660) 32G 黑色 移动联通电信4G手机","referenceTime":"2016-10-23 23:53:50","referenceType":"Product","referenceTypeId":0,"firstCategory":9987,"secondCategory":653,"thirdCategory":655,"replyCount":0,"score":5,"status":1,"title":"","usefulVoteCount":0,"uselessVoteCount":0,"userImage":"misc.360buyimg.com/lib/img/u/b62.gif","userImageUrl":"misc.360buyimg.com/lib/img/u/b62.gif","userLevelId":"62","userProvince":"","viewCount":0,"orderId":0,"isReplyGrade":false,"nickname":"丶***s","userClient":2,"images":[{"id":218211622,"associateId":136131801,"productId":0,"imgUrl":"//img30.360buyimg.com/n0/s128x96_jfs/t3364/75/631805377/82541/324f6173/580f14c3Naff69bc3.jpg","available":1,"pin":"","dealt":0,"imgTitle":"","isMain":0}],"showOrderComment":{"id":136131801,"guid":"9b92dca6-cdb8-41c9-b4e1-69c9020f1f49","content":"感觉上还可以毕竟京东自己的货 支持京东。用了一下午没有发现什么特别的问题<div class='uploadimgdiv'><img class='uploadimg' border='0'  src='http://img30.360buyimg.com/shaidan/jfs/t3364/75/631805377/82541/324f6173/580f14c3Naff69bc3.jpg' /></div>","creationTime":"2016-10-25 16:16:06","isTop":false,"referenceId":"3133817","referenceType":"Order","referenceTypeId":0,"firstCategory":0,"secondCategory":0,"thirdCategory":0,"replyCount":0,"score":0,"status":1,"title":"感觉上还可以毕竟京东自己的货 支持京东。","usefulVoteCount":0,"uselessVoteCount":0,"userProvince":"","viewCount":0,"orderId":0,"isReplyGrade":false,"userClient":0,"isDeal":1,"integral":-20,"userImgFlag":0,"anonymousFlag":1,"recommend":false,"userLevelColor":"#666666","userClientShow":"","isMobile":false},"mergeOrderStatus":2,"discussionId":136131801,"productColor":"黑色","productSize":"iPhone 7","imageCount":1,"integral":-20,"userImgFlag":0,"anonymousFlag":1,"userLevelName":"金牌会员","plusAvailable":103,"productSales":[],"recommend":false,"userLevelColor":"#666666","userClientShow":"来自京东iPhone客户端","isMobile":true,"days":2,"afterDays":0}]}