{"productAttr":null,"productCommentSummary":{"goodRateShow":97,"poorRateShow":2,"poorCountStr":"800+","averageScore":5,"generalCountStr":"700+","showCount":8700,"showCountStr":"8700+","goodCount":50000,"generalRate":0.014,"generalCount":700,"skuId":3133817,"goodCountStr":"5万+","poorRate":0.017,"afterCount":50,"goodRateStyle":145,"poorCount":800,"skuIds":null,"poorRateStyle":3,"generalRateStyle":2,"commentCountStr":"5.1万+","commentCount":51000,"productId":3133817,"afterCountStr":"50+","goodRate":0.969,"generalRateShow":1},"hotCommentTagStatistics":[{"id":1356036,"name":"系统流畅","status":0,"rid":15226,"productId":3133817,"count":867,"created":"2016-09-16 16:29:27","modified":"2017-03-02 10:59:53","type":0},{"id":1357450,"name":"外观漂亮","status":0,"rid":15225,"productId":3133817,"count":775,"created":"2016-09-18 09:29:54","modified":"2017-03-02 10:19:11","type":0},{"id":1357482,"name":"反应快","status":0,"rid":15224,"productId":3133817,"count":732,"created":"2016-09-18 09:54:40","modified":"2017-03-01 18:03:32","type":0},{"id":1357480,"name":"功能齐全","status":0,"rid":15231,"productId":3133817,"count":631,"created":"2016-09-18 09:54:40","modified":"2017-03-02 08:49:07","type":0},{"id":1356171,"name":"指纹识别","status":0,"rid":31384,"productId":3133817,"count":540,"created":"2016-09-16 19:33:13","modified":"2017-03-02 13:36:06","type":0},{"id":1356035,"name":"照相不错","status":0,"rid":15223,"productId":3133817,"count":531,"created":"2016-09-16 16:29:27","modified":"2017-03-01 15:38:57","type":0},{"id":1357481,"name":"分辨率高","status":0,"rid":15232,"productId":3133817,"count":453,"created":"2016-09-18 09:54:40","modified":"2017-03-02 10:59:53","type":0},{"id":1358321,"name":"音质好","status":0,"rid":15234,"productId":3133817,"count":442,"created":"2016-09-18 22:56:02","modified":"2017-03-01 15:38:57","type":0},{"id":1365225,"name":"通话质量好","status":0,"rid":15235,"productId":3133817,"count":422,"created":"2016-09-26 09:56:15","modified":"2017-03-02 10:26:30","type":0},{"id":1357451,"name":"信号稳定","status":0,"rid":15236,"productId":3133817,"count":415,"created":"2016-09-18 09:29:54","modified":"2017-03-02 10:59:53","type":0}],"jwotestProduct":"99","maxPage":5186,"score":0,"soType":5,"imageListCount":500,"vTagStatistics":[],"comments":[{"id":2048685152,"guid":"47b90328-f404-4dc5-b59e-6bc863f46ed9","content":"第一次在京东买手机，没有发现什么问题，希望是正品","creationTime":"2016-11-21 16:13:17","isTop":false,"referenceId":"3133817","referenceImage":"jfs/t3298/58/1622979569/120892/64989235/57d0d400Nfd249af4.jpg","referenceName":"Apple iPhone 7 (A1660) 32G 黑色 移动联通电信4G手机","referenceTime":"2016-11-09 19:02:49","referenceType":"Product","referenceTypeId":0,"firstCategory":9987,"secondCategory":653,"thirdCategory":655,"replyCount":0,"score":5,"status":1,"title":"","usefulVoteCount":0,"uselessVoteCount":0,"userImage":"misc.360buyimg.com/lib/img/u/b61.gif","userImageUrl":"misc.360buyimg.com/lib/img/u/b61.gif","userLevelId":"61","userProvince":"广东","viewCount":0,"orderId":0,"isReplyGrade":false,"nickname":"m***8","userClient":21,"productColor":"黑色","productSize":"iPhone 7","integral":-20,"userImgFlag":0,"anonymousFlag":1,"userLevelName":"银牌会员","plusAvailable":103,"productSales":[],"recommend":false,"userLevelColor":"#666666","userClientShow":"来自微信购物","isMobile":false,"days":12,"afterDays":0},{"id":2048619978,"guid":"ba8447de-0da2-4754-90bf-fcb02fb79061","content":"服务不错，下次还来！","creationTime":"2016-11-21 15:55:52","isTop":false,"referenceId":"3133817","referenceImage":"jfs/t3298/58/1622979569/120892/64989235/57d0d400Nfd249af4.jpg","referenceName":"Apple iPhone 7 (A1660) 32G 黑色 移动联通电信4G手机","referenceTime":"2016-10-29 19:20:45","referenceType":"Product","referenceTypeId":0,"firstCategory":9987,"secondCategory":653,"thirdCategory":655,"replyCount":0,"score":5,"status":1,"title":"","usefulVoteCount":0,"uselessVoteCount":0,"userImage":"misc.360buyimg.com/lib/img/u/b62.gif","userImageUrl":"misc.360buyimg.com/lib/img/u/b62.gif","userLevelId":"62","userProvince":"山东","viewCount":0,"orderId":0,"isReplyGrade":false,"nickname":"j***q","userClient":4,"productColor":"黑色","productSize":"iPhone 7","integral":-20,"userImgFlag":0,"anonymousFlag":1,"userLevelName":"金牌会员","plusAvailable":103,"productSales":[],"recommend":false,"userLevelColor":"#666666","userClientShow":"来自京东Android客户端","isMobile":true,"days":23,"afterDays":0},{"id":2048607055,"guid":"24132436-eed6-45c2-bac8-669390035805","content":"用了一周了'暂时没出现什么问题","creationTime":"2016-11-21 15:52:32","isTop":false,"referenceId":"3133817","referenceImage":"jfs/t3298/58/1622979569/120892/64989235/57d0d400Nfd249af4.jpg","referenceName":"Apple iPhone 7 (A1660) 32G 黑色 移动联通电信4G手机","referenceTime":"2016-11-13 07:00:29","referenceType":"Product","referenceTypeId":0,"firstCategory":9987,"secondCategory":653,"thirdCategory":655,"replyCount":0,"score":5,"status":1,"title":"","usefulVoteCount":0,"uselessVoteCount":0,"userImage":"storage.360buyimg.com/i.imageUpload/6a645f3432393430323630376235326231343637393436343233333035_sma.jpg","userImageUrl":"storage.360buyimg.com/i.imageUpload/6a645f3432393430323630376235326231343637393436343233333035_sma.jpg","userLevelId":"62","userProvince":"","viewCount":0,"orderId":0,"isReplyGrade":false,"nickname":"东***6","userClient":2,"productColor":"黑色","productSize":"iPhone 7","integral":-20,"userImgFlag":1,"anonymousFlag":1,"userLevelName":"金牌会员","plusAvailable":0,"productSales":[],"recommend":false,"userLevelColor":"#666666","userClientShow":"来自京东iPhone客户端","isMobile":true,"days":8,"afterDays":0},{"id":2048573570,"guid":"a2e87fa4-3b87-41d2-80b4-88a3ff252a9c","content":"物流快，质量好，已经买的第二个了","creationTime":"2016-11-21 15:43:44","isTop":false,"referenceId":"3133817","referenceImage":"jfs/t3298/58/1622979569/120892/64989235/57d0d400Nfd249af4.jpg","referenceName":"Apple iPhone 7 (A1660) 32G 黑色 移动联通电信4G手机","referenceTime":"2016-10-31 23:14:36","referenceType":"Product","referenceTypeId":0,"firstCategory":9987,"secondCategory":653,"thirdCategory":655,"replyCount":0,"score":5,"status":1,"title":"","usefulVoteCount":0,"uselessVoteCount":0,"userImage":"storage.360buyimg.com/i.imageUpload/6a645f3436663936363635303661373231343234363032353236373934_sma.jpg","userImageUrl":"storage.360buyimg.com/i.imageUpload/6a645f3436663936363635303661373231343234363032353236373934_sma.jpg","userLevelId":"62","userProvince":"河北","viewCount":0,"orderId":0,"isReplyGrade":false,"nickname":"j***v","userClient":2,"productColor":"黑色","productSize":"iPhone 7","integral":-20,"userImgFlag":1,"anonymousFlag":1,"userLevelName":"金牌会员","plusAvailable":103,"productSales":[],"recommend":false,"userLevelColor":"#666666","userClientShow":"来自京东iPhone客户端","isMobile":true,"days":21,"afterDays":0},{"id":2048556006,"guid":"7a9147ab-e4a1-4e60-b541-e233f1b55a8e","content":"不知道行不行  以后再评","creationTime":"2016-11-21 15:39:25","isTop":false,"referenceId":"3133817","referenceImage":"jfs/t3298/58/1622979569/120892/64989235/57d0d400Nfd249af4.jpg","referenceName":"Apple iPhone 7 (A1660) 32G 黑色 移动联通电信4G手机","referenceTime":"2016-11-11 01:02:13","referenceType":"Product","referenceTypeId":0,"firstCategory":9987,"secondCategory":653,"thirdCategory":655,"replyCount":0,"score":2,"status":1,"title":"","usefulVoteCount":0,"uselessVoteCount":0,"userImage":"misc.360buyimg.com/lib/img/u/b62.gif","userImageUrl":"misc.360buyimg.com/lib/img/u/b62.gif","userLevelId":"62","userProvince":"","viewCount":0,"orderId":0,"isReplyGrade":false,"nickname":"叶***巴","userClient":2,"productColor":"黑色","productSize":"iPhone 7","integral":-20,"userImgFlag":0,"anonymousFlag":1,"userLevelName":"金牌会员","plusAvailable":103,"productSales":[],"recommend":false,"userLevelColor":"#666666","userClientShow":"来自京东iPhone客户端","isMobile":true,"days":10,"afterDays":0},{"id":2048555078,"guid":"c32ea03d-3bf8-4354-9000-02113358c7f4","content":"物流一流东西一流，没毛病，相信京东","creationTime":"2016-11-21 15:39:12","isTop":false,"referenceId":"3133817","referenceImage":"jfs/t3298/58/1622979569/120892/64989235/57d0d400Nfd249af4.jpg","referenceName":"Apple iPhone 7 (A1660) 32G 黑色 移动联通电信4G手机","referenceTime":"2016-11-09 15:25:51","referenceType":"Product","referenceTypeId":0,"firstCategory":9987,"secondCategory":653,"thirdCategory":655,"replyCount":0,"score":5,"status":1,"title":"","usefulVoteCount":0,"uselessVoteCount":0,"userImage":"storage.360buyimg.com/i.imageUpload/31383638363535363930355f70776831343734323433343036383438_sma.jpg","userImageUrl":"storage.360buyimg.com/i.imageUpload/31383638363535363930355f70776831343734323433343036383438_sma.jpg","userLevelId":"62","userProvince":"","viewCount":0,"orderId":0,"isReplyGrade":false,"nickname":"江***伟","userClient":2,"images":[{"id":237372734,"associateId":148365769,"productId":0,"imgUrl":"//img30.360buyimg.com/n0/s128x96_jfs/t3508/305/1860676708/96004/8a90e3b9/5832a4a0Nec364ba8.jpg","available":1,"pin":"","dealt":0,"imgTitle":"","isMain":0}],"showOrderComment":{"id":148365769,"guid":"c784f192-6808-4775-9a50-7bc4851a54a8","content":"物流一流东西一流，没毛病，相信京东<div class='uploadimgdiv'><img class='uploadimg' border='0'  src='http://img30.360buyimg.com/shaidan/jfs/t3508/305/1860676708/96004/8a90e3b9/5832a4a0Nec364ba8.jpg' /></div>","creationTime":"2016-11-21 15:39:12","isTop":false,"referenceId":"3133817","referenceType":"Order","referenceTypeId":0,"firstCategory":0,"secondCategory":0,"thirdCategory":0,"replyCount":0,"score":0,"status":1,"title":"物流一流东西一流，没毛病，相信京东","usefulVoteCount":0,"uselessVoteCount":0,"userProvince":"","viewCount":0,"orderId":0,"isReplyGrade":false,"userClient":2,"isDeal":1,"integral":-20,"userImgFlag":0,"anonymousFlag":1,"recommend":false,"userLevelColor":"#666666","userClientShow":"来自京东iPhone客户端","isMobile":true},"mergeOrderStatus":2,"discussionId":148365769,"productColor":"黑色","productSize":"iPhone 7","imageCount":1,"integral":-20,"userImgFlag":1,"anonymousFlag":1,"userLevelName":"金牌会员","plusAvailable":0,"productSales":[],"recommend":false,"userLevelColor":"#666666","userClientShow":"来自京东iPhone客户端","isMobile":true,"days":12,"afterDays":0},{"id":2048548961,"guid":"a783159e-ae86-4bd5-88f5-a1660bc73e0e","content":"没毛病？666666666","creationTime":"2016-11-21 15:37:25","isTop":false,"referenceId":"3133817","referenceImage":"jfs/t3298/58/1622979569/120892/64989235/57d0d400Nfd249af4.jpg","referenceName":"Apple iPhone 7 (A1660) 32G 黑色 移动联通电信4G手机","referenceTime":"2016-10-23 18:24:16","referenceType":"Product","referenceTypeId":0,"firstCategory":9987,"secondCategory":653,"thirdCategory":655,"replyCount":0,"score":5,"status":1,"title":"","usefulVoteCount":0,"uselessVoteCount":0,"userImage":"misc.360buyimg.com/lib/img/u/b105.gif","userImageUrl":"misc.360buyimg.com/lib/img/u/b105.gif","userLevelId":"105","userProvince":"浙江","viewCount":0,"orderId":0,"isReplyGrade":false,"nickname":"s***睛","userClient":2,"productColor":"黑色","productSize":"iPhone 7","integral":-20,"userImgFlag":0,"anonymousFlag":1,"userLevelName":"钻石会员","plusAvailable":103,"productSales":[],"recommend":false,"userLevelColor":"#666666","userClientShow":"来自京东iPhone客户端","isMobile":true,"days":29,"afterDays":0},{"id":2048545347,"guid":"2df5fcf9-7355-4bb0-b94f-b140f8d00e68","content":"不错性价比很高","creationTime":"2016-11-21 15:36:38","isTop":false,"referenceId":"3133817","referenceImage":"jfs/t3298/58/1622979569/120892/64989235/57d0d400Nfd249af4.jpg","referenceName":"Apple iPhone 7 (A1660) 32G 黑色 移动联通电信4G手机","referenceTime":"2016-11-11 11:36:30","referenceType":"Product","referenceTypeId":0,"firstCategory":9987,"secondCategory":653,"thirdCategory":655,"replyCount":0,"score":5,"status":1,"title":"","usefulVoteCount":0,"uselessVoteCount":0,"userImage":"storage.360buyimg.com/i.imageUpload/31383636343532393932365f7031343238303533383637373632_sma.jpg","userImageUrl":"storage.360buyimg.com/i.imageUpload/31383636343532393932365f7031343238303533383637373632_sma.jpg","userLevelId":"62","userProvince":"广东","viewCount":0,"orderId":0,"isReplyGrade":false,"nickname":"叫***生","userClient":2,"productColor":"黑色","productSize":"iPhone 7","integral":0,"userImgFlag":1,"anonymousFlag":1,"userLevelName":"金牌会员","plusAvailable":103,"productSales":[],"recommend":false,"userLevelColor":"#666666","userClientShow":"来自京东iPhone客户端","isMobile":true,"days":10,"afterDays":0},{"id":2048543388,"guid":"9560a200-a370-4c4e-8a80-bb9de130350f","content":"苹果，还不错?","creationTime":"2016-11-21 15:36:03","isTop":false,"referenceId":"3133817","referenceImage":"jfs/t3298/58/1622979569/120892/64989235/57d0d400Nfd249af4.jpg","referenceName":"Apple iPhone 7 (A1660) 32G 黑色 移动联通电信4G手机","referenceTime":"2016-11-20 10:25:54","referenceType":"Product","referenceTypeId":0,"firstCategory":9987,"secondCategory":653,"thirdCategory":655,"replyCount":0,"score":5,"status":1,"title":"","usefulVoteCount":0,"uselessVoteCount":0,"userImage":"storage.360buyimg.com/i.imageUpload/6a645f3734393466393333363564306631343139373732313730303738_sma.jpg","userImageUrl":"storage.360buyimg.com/i.imageUpload/6a645f3734393466393333363564306631343139373732313730303738_sma.jpg","userLevelId":"105","userProvince":"","viewCount":0,"orderId":0,"isReplyGrade":false,"nickname":"H***者","userClient":4,"productColor":"黑色","productSize":"iPhone 7","integral":0,"userImgFlag":1,"anonymousFlag":1,"userLevelName":"钻石会员","plusAvailable":103,"productSales":[],"recommend":false,"userLevelColor":"#666666","userClientShow":"来自京东Android客户端","isMobile":true,"days":1,"afterDays":0},{"id":2048520141,"guid":"244b3e14-9221-417d-a594-3dcdf9c3ec09","content":"正品","creationTime":"2016-11-21 15:30:05","isTop":false,"referenceId":"3133817","referenceImage":"jfs/t3298/58/1622979569/120892/64989235/57d0d400Nfd249af4.jpg","referenceName":"Apple iPhone 7 (A1660) 32G 黑色 移动联通电信4G手机","referenceTime":"2016-10-17 10:18:32","referenceType":"Product","referenceTypeId":0,"firstCategory":9987,"secondCategory":653,"thirdCategory":655,"replyCount":0,"score":5,"status":1,"title":"","usefulVoteCount":0,"uselessVoteCount":0,"userImage":"misc.360buyimg.com/lib/img/u/b62.gif","userImageUrl":"misc.360buyimg.com/lib/img/u/b62.gif","userLevelId":"62","userProvince":"","viewCount":0,"orderId":0,"isReplyGrade":false,"nickname":"S***n","userClient":0,"commentTags":[{"id":13296805,"name":"音质好","pin":"","status":0,"rid":15234,"productId":3133817,"commentId":2048520141,"created":"2016-11-21 15:30:21","modified":"2016-11-21 15:30:21"},{"id":13296806,"name":"反应快","pin":"","status":0,"rid":15224,"productId":3133817,"commentId":2048520141,"created":"2016-11-21 15:30:21","modified":"2016-11-21 15:30:21"},{"id":13296807,"name":"备用机","pin":"","status":0,"rid":31382,"productId":3133817,"commentId":2048520141,"created":"2016-11-21 15:30:21","modified":"2016-11-21 15:30:21"},{"id":13296808,"name":"老人机","pin":"","status":0,"rid":31381,"productId":3133817,"commentId":2048520141,"created":"2016-11-21 15:30:21","modified":"2016-11-21 15:30:21"},{"id":13296809,"name":"信号稳定","pin":"","status":0,"rid":15236,"productId":3133817,"commentId":2048520141,"created":"2016-11-21 15:30:21","modified":"2016-11-21 15:30:21"}],"productColor":"黑色","productSize":"iPhone 7","integral":0,"userImgFlag":0,"anonymousFlag":1,"userLevelName":"金牌会员","plusAvailable":0,"productSales":[],"recommend":false,"userLevelColor":"#666666","userClientShow":"","isMobile":false,"days":35,"afterDays":0}]}