{"productAttr":null,"productCommentSummary":{"goodRateShow":97,"poorRateShow":2,"poorCountStr":"800+","averageScore":5,"generalCountStr":"700+","showCount":8700,"showCountStr":"8700+","goodCount":50000,"generalRate":0.014,"generalCount":700,"skuId":3133817,"goodCountStr":"5万+","poorRate":0.017,"afterCount":50,"goodRateStyle":145,"poorCount":800,"skuIds":null,"poorRateStyle":3,"generalRateStyle":2,"commentCountStr":"5.1万+","commentCount":51000,"productId":3133817,"afterCountStr":"50+","goodRate":0.969,"generalRateShow":1},"hotCommentTagStatistics":[{"id":1356036,"name":"系统流畅","status":0,"rid":15226,"productId":3133817,"count":866,"created":"2016-09-16 16:29:27","modified":"2017-03-01 13:47:36","type":0},{"id":1357450,"name":"外观漂亮","status":0,"rid":15225,"productId":3133817,"count":774,"created":"2016-09-18 09:29:54","modified":"2017-02-28 14:52:06","type":0},{"id":1357482,"name":"反应快","status":0,"rid":15224,"productId":3133817,"count":732,"created":"2016-09-18 09:54:40","modified":"2017-03-01 18:03:32","type":0},{"id":1357480,"name":"功能齐全","status":0,"rid":15231,"productId":3133817,"count":631,"created":"2016-09-18 09:54:40","modified":"2017-03-02 08:49:07","type":0},{"id":1356171,"name":"指纹识别","status":0,"rid":31384,"productId":3133817,"count":538,"created":"2016-09-16 19:33:13","modified":"2017-03-02 08:49:07","type":0},{"id":1356035,"name":"照相不错","status":0,"rid":15223,"productId":3133817,"count":531,"created":"2016-09-16 16:29:27","modified":"2017-03-01 15:38:57","type":0},{"id":1357481,"name":"分辨率高","status":0,"rid":15232,"productId":3133817,"count":452,"created":"2016-09-18 09:54:40","modified":"2017-03-01 15:38:57","type":0},{"id":1358321,"name":"音质好","status":0,"rid":15234,"productId":3133817,"count":442,"created":"2016-09-18 22:56:02","modified":"2017-03-01 15:38:57","type":0},{"id":1365225,"name":"通话质量好","status":0,"rid":15235,"productId":3133817,"count":421,"created":"2016-09-26 09:56:15","modified":"2017-03-01 13:23:10","type":0},{"id":1357451,"name":"信号稳定","status":0,"rid":15236,"productId":3133817,"count":414,"created":"2016-09-18 09:29:54","modified":"2017-03-01 19:39:28","type":0}],"jwotestProduct":"99","maxPage":5180,"score":0,"soType":5,"imageListCount":500,"vTagStatistics":[],"comments":[{"id":2123620969,"guid":"456107a9-eee8-4a0e-b796-b5d1ccf5add5","content":"京东品质一直都值得信赖","creationTime":"2016-12-14 19:19:08","isTop":false,"referenceId":"3133817","referenceImage":"jfs/t3298/58/1622979569/120892/64989235/57d0d400Nfd249af4.jpg","referenceName":"Apple iPhone 7 (A1660) 32G 黑色 移动联通电信4G手机","referenceTime":"2016-12-13 20:51:06","referenceType":"Product","referenceTypeId":0,"firstCategory":9987,"secondCategory":653,"thirdCategory":655,"replyCount":0,"score":5,"status":1,"title":"","usefulVoteCount":0,"uselessVoteCount":0,"userImage":"storage.360buyimg.com/i.imageUpload/d3f7d1a7cbab31343233313232343431353238_sma.jpg","userImageUrl":"storage.360buyimg.com/i.imageUpload/d3f7d1a7cbab31343233313232343431353238_sma.jpg","userLevelId":"105","userProvince":"北京","viewCount":0,"orderId":0,"isReplyGrade":false,"nickname":"雨***霜","userClient":2,"productColor":"黑色","productSize":"iPhone 7","integral":-20,"userImgFlag":1,"anonymousFlag":1,"userLevelName":"PLUS会员","plusAvailable":201,"productSales":[],"recommend":false,"userLevelColor":"#e1a10a","userClientShow":"来自京东iPhone客户端","isMobile":true,"days":1,"afterDays":0},{"id":2123619975,"guid":"0d5e5a23-80e7-4b6e-a0bb-544b24997143","content":"还行吧，没赶上双11优惠","creationTime":"2016-12-14 19:18:52","isTop":false,"referenceId":"3133817","referenceImage":"jfs/t3298/58/1622979569/120892/64989235/57d0d400Nfd249af4.jpg","referenceName":"Apple iPhone 7 (A1660) 32G 黑色 移动联通电信4G手机","referenceTime":"2016-11-14 09:07:44","referenceType":"Product","referenceTypeId":0,"firstCategory":9987,"secondCategory":653,"thirdCategory":655,"replyCount":0,"score":5,"status":1,"title":"","usefulVoteCount":0,"uselessVoteCount":0,"userImage":"storage.360buyimg.com/i.imageUpload/6a645f3531316634336464333039643231343838333335313338313738_sma.jpg","userImageUrl":"storage.360buyimg.com/i.imageUpload/6a645f3531316634336464333039643231343838333335313338313738_sma.jpg","userLevelId":"62","userProvince":"","viewCount":0,"orderId":0,"isReplyGrade":false,"nickname":"回***_","userClient":2,"productColor":"黑色","productSize":"iPhone 7","integral":-20,"userImgFlag":1,"anonymousFlag":1,"userLevelName":"金牌会员","plusAvailable":0,"productSales":[],"recommend":false,"userLevelColor":"#666666","userClientShow":"来自京东iPhone客户端","isMobile":true,"days":30,"afterDays":0},{"id":2123611708,"guid":"b246ee70-6227-4767-8ddc-22b212be6a74","content":"很好，相信京东，后面追","creationTime":"2016-12-14 19:16:34","isTop":false,"referenceId":"3133817","referenceImage":"jfs/t3298/58/1622979569/120892/64989235/57d0d400Nfd249af4.jpg","referenceName":"Apple iPhone 7 (A1660) 32G 黑色 移动联通电信4G手机","referenceTime":"2016-12-12 22:04:45","referenceType":"Product","referenceTypeId":0,"firstCategory":9987,"secondCategory":653,"thirdCategory":655,"replyCount":0,"score":5,"status":1,"title":"","usefulVoteCount":1,"uselessVoteCount":0,"userImage":"storage.360buyimg.com/i.imageUpload/74616e6b656a69616e31333738393039343538343830_sma.jpg","userImageUrl":"storage.360buyimg.com/i.imageUpload/74616e6b656a69616e31333738393039343538343830_sma.jpg","userLevelId":"105","userProvince":"重庆","viewCount":0,"orderId":0,"isReplyGrade":false,"nickname":"g***4","userClient":2,"productColor":"黑色","productSize":"iPhone 7","integral":-20,"userImgFlag":1,"anonymousFlag":1,"userLevelName":"钻石会员","plusAvailable":0,"productSales":[],"recommend":false,"userLevelColor":"#666666","userClientShow":"来自京东iPhone客户端","isMobile":true,"days":2,"afterDays":0},{"id":2123576970,"guid":"73d777e5-50e7-4691-96f6-7511e3b4f1d2","content":"好好好好好好好","creationTime":"2016-12-14 19:06:47","isTop":false,"referenceId":"3133817","referenceImage":"jfs/t3298/58/1622979569/120892/64989235/57d0d400Nfd249af4.jpg","referenceName":"Apple iPhone 7 (A1660) 32G 黑色 移动联通电信4G手机","referenceTime":"2016-12-13 11:33:09","referenceType":"Product","referenceTypeId":0,"firstCategory":9987,"secondCategory":653,"thirdCategory":655,"replyCount":0,"score":5,"status":1,"title":"","usefulVoteCount":0,"uselessVoteCount":0,"userImage":"storage.360buyimg.com/i.imageUpload/6a645f3638383466636666656631316531343630393632313639393132_sma.jpg","userImageUrl":"storage.360buyimg.com/i.imageUpload/6a645f3638383466636666656631316531343630393632313639393132_sma.jpg","userLevelId":"62","userProvince":"江苏","viewCount":0,"orderId":0,"isReplyGrade":false,"nickname":"赵***z","userClient":2,"productColor":"黑色","productSize":"iPhone 7","integral":0,"userImgFlag":1,"anonymousFlag":1,"userLevelName":"金牌会员","plusAvailable":103,"productSales":[],"recommend":false,"userLevelColor":"#666666","userClientShow":"来自京东iPhone客户端","isMobile":true,"days":1,"afterDays":0},{"id":2123567666,"guid":"37ff9489-1de9-4687-9c9b-7045ccc69ad6","content":"商品很好，物流很快，很满意。","creationTime":"2016-12-14 19:04:07","isTop":false,"referenceId":"3133817","referenceImage":"jfs/t3298/58/1622979569/120892/64989235/57d0d400Nfd249af4.jpg","referenceName":"Apple iPhone 7 (A1660) 32G 黑色 移动联通电信4G手机","referenceTime":"2016-12-12 19:05:14","referenceType":"Product","referenceTypeId":0,"firstCategory":9987,"secondCategory":653,"thirdCategory":655,"replyCount":0,"score":5,"status":1,"title":"","usefulVoteCount":0,"uselessVoteCount":0,"userImage":"misc.360buyimg.com/lib/img/u/b105.gif","userImageUrl":"misc.360buyimg.com/lib/img/u/b105.gif","userLevelId":"105","userProvince":"","viewCount":0,"orderId":0,"isReplyGrade":false,"nickname":"y***e","userClient":2,"productColor":"黑色","productSize":"iPhone 7","integral":-20,"userImgFlag":0,"anonymousFlag":1,"userLevelName":"钻石会员","plusAvailable":103,"productSales":[],"recommend":false,"userLevelColor":"#666666","userClientShow":"来自京东iPhone客户端","isMobile":true,"days":2,"afterDays":0},{"id":2123567554,"guid":"fb75af62-0cde-4b8d-9904-a55c5accbd74","content":"还在摸索，苹果手机秒杀一切，京东物流配送体系秒杀一切","creationTime":"2016-12-14 19:04:07","isTop":false,"referenceId":"3133817","referenceImage":"jfs/t3298/58/1622979569/120892/64989235/57d0d400Nfd249af4.jpg","referenceName":"Apple iPhone 7 (A1660) 32G 黑色 移动联通电信4G手机","referenceTime":"2016-12-12 18:05:46","referenceType":"Product","referenceTypeId":0,"firstCategory":9987,"secondCategory":653,"thirdCategory":655,"replyCount":0,"score":5,"status":1,"title":"","usefulVoteCount":0,"uselessVoteCount":0,"userImage":"storage.360buyimg.com/i.imageUpload/313231313531333437362d33333637303331343637363137323332373039_sma.jpg","userImageUrl":"storage.360buyimg.com/i.imageUpload/313231313531333437362d33333637303331343637363137323332373039_sma.jpg","userLevelId":"105","userProvince":"","viewCount":0,"orderId":0,"isReplyGrade":false,"nickname":"劳***8","userClient":2,"images":[{"id":249984164,"associateId":156655531,"productId":0,"imgUrl":"//img30.360buyimg.com/n0/s128x96_jfs/t3049/74/4697263898/106075/ed675899/58512725N55607e42.jpg","available":1,"pin":"","dealt":0,"imgTitle":"","isMain":0}],"showOrderComment":{"id":156655531,"guid":"6efb04e2-b395-4dc8-b3ac-891996956a85","content":"还在摸索，苹果手机秒杀一切，京东物流配送体系秒杀一切<div class='uploadimgdiv'><img class='uploadimg' border='0'  src='http://img30.360buyimg.com/shaidan/jfs/t3049/74/4697263898/106075/ed675899/58512725N55607e42.jpg' /></div>","creationTime":"2016-12-14 19:04:07","isTop":false,"referenceId":"3133817","referenceType":"Order","referenceTypeId":0,"firstCategory":0,"secondCategory":0,"thirdCategory":0,"replyCount":0,"score":0,"status":1,"title":"还在摸索，苹果手机秒杀一切，京东物流配送...","usefulVoteCount":0,"uselessVoteCount":0,"userProvince":"","viewCount":0,"orderId":0,"isReplyGrade":false,"userClient":2,"isDeal":1,"integral":-20,"userImgFlag":0,"anonymousFlag":1,"recommend":false,"userLevelColor":"#666666","userClientShow":"来自京东iPhone客户端","isMobile":true},"mergeOrderStatus":2,"discussionId":156655531,"productColor":"黑色","productSize":"iPhone 7","imageCount":1,"integral":-20,"userImgFlag":1,"anonymousFlag":1,"userLevelName":"钻石会员","afterUserComment":{"tableNames":{},"forceRead2Writer":false,"id":10368448,"productId":3133817,"orderId":47246678059,"commentId":2123567554,"status":1,"pin":"1211513476-336703","clientType":2,"ip":"222.65.156.143","anonymous":1,"dealt":0,"created":"2016-12-16 21:11:57","modified":"2016-12-16 21:11:57","hAfterUserComment":{"rowKey":"2610368448","id":10368448,"content":"苹果手机值得拥有","discussionId":157546403}},"plusAvailable":0,"productSales":[],"recommend":false,"userLevelColor":"#666666","userClientShow":"来自京东iPhone客户端","isMobile":true,"days":2,"afterDays":4},{"id":2123540707,"guid":"645e00a4-92e8-4f64-a2ea-a2ebf9514186","content":"我为什么喜欢在京东买东西，因为今天买明天就可以送到。我为什么每个商品的评价都一样，因为在京东买的东西太多太多了，导致积累了很多未评价的订单，所以我统一用段话作为评价内容。京东购物这么久，有买到很好的产品，也有买到比较坑的产品，如果我用这段话来评价，说明这款产品没问题，至少85分以上，而比较垃圾的产品，我绝对不会偷懒到复制粘贴评价，我绝对会用心的差评，这样其他消费者在购买的时候会作为参考，会影响该商品销量，而商家也会因此改进商品质量。","creationTime":"2016-12-14 18:56:21","isTop":false,"referenceId":"3133817","referenceImage":"jfs/t3298/58/1622979569/120892/64989235/57d0d400Nfd249af4.jpg","referenceName":"Apple iPhone 7 (A1660) 32G 黑色 移动联通电信4G手机","referenceTime":"2016-11-09 20:31:01","referenceType":"Product","referenceTypeId":0,"firstCategory":9987,"secondCategory":653,"thirdCategory":655,"replyCount":0,"score":5,"status":1,"title":"","usefulVoteCount":0,"uselessVoteCount":0,"userImage":"storage.360buyimg.com/i.imageUpload/31353639353938373635395f7031343333383533383535383234_sma.jpg","userImageUrl":"storage.360buyimg.com/i.imageUpload/31353639353938373635395f7031343333383533383535383234_sma.jpg","userLevelId":"105","userProvince":"福建","viewCount":0,"orderId":0,"isReplyGrade":false,"nickname":"j***r","userClient":4,"productColor":"黑色","productSize":"iPhone 7","integral":-20,"userImgFlag":1,"anonymousFlag":1,"userLevelName":"PLUS会员","plusAvailable":201,"productSales":[],"recommend":false,"userLevelColor":"#e1a10a","userClientShow":"来自京东Android客户端","isMobile":true,"days":35,"afterDays":0},{"id":2123539388,"guid":"b71d804e-837e-4d3e-8611-2e04a62405fc","content":"包装不敢恭维 发票也没有","creationTime":"2016-12-14 18:56:00","isTop":false,"referenceId":"3133817","referenceImage":"jfs/t3298/58/1622979569/120892/64989235/57d0d400Nfd249af4.jpg","referenceName":"Apple iPhone 7 (A1660) 32G 黑色 移动联通电信4G手机","referenceTime":"2016-12-14 00:57:28","referenceType":"Product","referenceTypeId":0,"firstCategory":9987,"secondCategory":653,"thirdCategory":655,"replyCount":0,"score":5,"status":1,"title":"","usefulVoteCount":0,"uselessVoteCount":0,"userImage":"storage.360buyimg.com/i.imageUpload/63746c6f7665646f6e673230303831343235333638303634393731_sma.jpg","userImageUrl":"storage.360buyimg.com/i.imageUpload/63746c6f7665646f6e673230303831343235333638303634393731_sma.jpg","userLevelId":"62","userProvince":"河南","viewCount":0,"orderId":0,"isReplyGrade":false,"nickname":"c***8","userClient":4,"productColor":"黑色","productSize":"iPhone 7","integral":-20,"userImgFlag":1,"anonymousFlag":1,"userLevelName":"金牌会员","plusAvailable":103,"productSales":[],"recommend":false,"userLevelColor":"#666666","userClientShow":"来自京东Android客户端","isMobile":true,"days":0,"afterDays":0},{"id":2123537717,"guid":"232c7c0c-6e4b-4f36-9ad0-5756bde376a6","content":"和想象中一样 不错","creationTime":"2016-12-14 18:55:24","isTop":false,"referenceId":"3133817","referenceImage":"jfs/t3298/58/1622979569/120892/64989235/57d0d400Nfd249af4.jpg","referenceName":"Apple iPhone 7 (A1660) 32G 黑色 移动联通电信4G手机","referenceTime":"2016-12-13 12:57:57","referenceType":"Product","referenceTypeId":0,"firstCategory":9987,"secondCategory":653,"thirdCategory":655,"replyCount":0,"score":5,"status":1,"title":"","usefulVoteCount":2,"uselessVoteCount":0,"userImage":"storage.360buyimg.com/i.imageUpload/7764614c564f6f694e6e63774b5731343837303837323031393632_sma.jpg","userImageUrl":"storage.360buyimg.com/i.imageUpload/7764614c564f6f694e6e63774b5731343837303837323031393632_sma.jpg","userLevelId":"62","userProvince":"","viewCount":0,"orderId":0,"isReplyGrade":false,"nickname":"k***n","userClient":21,"productColor":"黑色","productSize":"iPhone 7","integral":0,"userImgFlag":1,"anonymousFlag":1,"userLevelName":"PLUS会员[试用]","plusAvailable":101,"productSales":[],"recommend":false,"userLevelColor":"#e1a10a","userClientShow":"来自微信购物","isMobile":false,"days":1,"afterDays":0},{"id":2123526633,"guid":"7d83ad49-0a5f-4ac1-ae13-6d0599fbd578","content":"还好","creationTime":"2016-12-14 18:52:15","isTop":false,"referenceId":"3133817","referenceImage":"jfs/t3298/58/1622979569/120892/64989235/57d0d400Nfd249af4.jpg","referenceName":"Apple iPhone 7 (A1660) 32G 黑色 移动联通电信4G手机","referenceTime":"2016-11-11 13:08:58","referenceType":"Product","referenceTypeId":0,"firstCategory":9987,"secondCategory":653,"thirdCategory":655,"replyCount":0,"score":5,"status":1,"title":"","usefulVoteCount":0,"uselessVoteCount":0,"userImage":"misc.360buyimg.com/lib/img/u/b61.gif","userImageUrl":"misc.360buyimg.com/lib/img/u/b61.gif","userLevelId":"61","userProvince":"","viewCount":0,"orderId":0,"isReplyGrade":false,"nickname":"j***u","userClient":2,"productColor":"黑色","productSize":"iPhone 7","integral":0,"userImgFlag":0,"anonymousFlag":1,"userLevelName":"银牌会员","plusAvailable":0,"productSales":[],"recommend":false,"userLevelColor":"#666666","userClientShow":"来自京东iPhone客户端","isMobile":true,"days":33,"afterDays":0}]}